LogisticRegression/Accuracy.py
LogisticRegression/Cost.py
LogisticRegression/Optimize.py
LogisticRegression/Predict.py
LogisticRegression/Sigmoid.py
LogisticRegression/__init__.py
LogisticRegression_PavanAdapa-1.0.3.dist-info/LICENSE
LogisticRegression_PavanAdapa-1.0.3.dist-info/METADATA
LogisticRegression_PavanAdapa-1.0.3.dist-info/WHEEL
LogisticRegression_PavanAdapa-1.0.3.dist-info/top_level.txt
LogisticRegression_PavanAdapa-1.0.3.dist-info/RECORD
