Metadata-Version: 2.1
Name: LogisticRegression-PavanAdapa
Version: 1.0.3
Summary: Package containing functions for logistic Regression
Home-page: https://github.com/pavanadapa/LogisticRegression
Author: Pavan Kumar Adapa
Author-email: Pavan.adapa@uconn.edu
License: UNKNOWN
Project-URL: Git, https://github.com/pavanadapa/LogisticRegression
Platform: UNKNOWN
Classifier: Programming Language :: Python :: 3
Classifier: License :: OSI Approved :: MIT License
Classifier: Operating System :: OS Independent
Requires-Python: >=3.6
License-File: LICENSE
